{
    "keep": {
        "days": true,
        "amount": 14
    },
    "auditLog": "E:\\Assignments L2 B2\\Assignment 8\\flat-sharing-server\\logs\\winston\\successes\\.f8ad26ef35d49e829b3c21c8d4dfdeec429dd4bd-audit.json",
    "files": [
        {
            "date": 1716361898937,
            "name": "E:\\Assignments L2 B2\\Assignment 8\\flat-sharing-server\\logs\\winston\\successes\\FSS-2024-22-05-13-success.log",
            "hash": "0a3ebce11b25661f194a2df02f150fd1e9fdb47ace0e42ad35590461fa632e76"
        }
    ],
    "hashType": "sha256"
}